[{"full_picture":"https://scontent-iad3-1.xx.fbcdn.net/v/t39.30808-6/459030657_18050898748855288_5744409880415558845_n.jpg?stp=dst-jpegr_p720x720&_nc_cat=102&ccb=1-7&_nc_sid=127cfc&_nc_ohc=94gPxcysF6cQ7kNvgGcUCfW&se=-1&_nc_ht=scontent-iad3-1.xx&edm=AKK4YLsEAAAA&oh=00_AYDMb6NtEA1l0wRFYZrnf5dj5iizwsGWXrJygcObfNNcqA&oe=66E56053","attachments":{"data":[{"description":"Liikuntasalien ohella yksi Blingin tärkeimmistä paikoista on erään jäsenemme peräkontti! Siellä kulkee kaikki mitä FC Bling Bling tarvitsee, pallot, peliliivit, ensiapu ja hyvin paljon myös kaikkea muuta! Tällä kertaa peräkontin täyttää uudet Blingero-pelipaidat jotka pääsevät ensikertaa tositoimiin jo lauantaina kun blingiläiset suuntaavat kohti  Vantaata ja Unelmacuppia.\n#varustevastaava #pelipaidat #topwise","media":{"image":{"height":900,"src":"https://scontent-iad3-1.xx.fbcdn.net/v/t39.30808-6/459030657_18050898748855288_5744409880415558845_n.jpg?stp=dst-jpegr_p720x720&_nc_cat=102&ccb=1-7&_nc_sid=127cfc&_nc_ohc=94gPxcysF6cQ7kNvgGcUCfW&se=-1&_nc_ht=scontent-iad3-1.xx&edm=AKK4YLsEAAAA&oh=00_AYDMb6NtEA1l0wRFYZrnf5dj5iizwsGWXrJygcObfNNcqA&oe=66E56053","width":720}},"target":{"id":"1013305270591248","url":"https://www.facebook.com/photo.php?fbid=1013305270591248&set=a.208567717731678&type=3"},"type":"photo","url":"https://www.facebook.com/photo.php?fbid=1013305270591248&set=a.208567717731678&type=3"}]},"message":"Liikuntasalien ohella yksi Blingin tärkeimmistä paikoista on erään jäsenemme peräkontti! Siellä kulkee kaikki mitä FC Bling Bling tarvitsee, pallot, peliliivit, ensiapu ja hyvin paljon myös kaikkea muuta! Tällä kertaa peräkontin täyttää uudet Blingero-pelipaidat jotka pääsevät ensikertaa tositoimiin jo lauantaina kun blingiläiset suuntaavat kohti  Vantaata ja Unelmacuppia.\n#varustevastaava #pelipaidat #topwise","created_time":"2024-09-09T11:02:18+0000","id":"112275979305828_1013305293924579"},{"full_picture":"https://scontent-iad3-1.xx.fbcdn.net/v/t39.30808-6/458160636_18050213749855288_4628907832212813857_n.jpg?stp=dst-jpg_p720x720&_nc_cat=101&ccb=1-7&_nc_sid=127cfc&_nc_ohc=9QkSHhPb2mkQ7kNvgGN-rPE&_nc_ht=scontent-iad3-1.xx&edm=AKK4YLsEAAAA&oh=00_AYCvkE18ysuC5BPjq_1BV4cIScD-O4Z4bMbdOzUi472zrQ&oe=66E5696D","attachments":{"data":[{"description":"Syksyn ekat futsalit. Hikisen hauskaa hommaa!","media":{"image":{"height":900,"src":"https://scontent-iad3-1.xx.fbcdn.net/v/t39.30808-6/458160636_18050213749855288_4628907832212813857_n.jpg?stp=dst-jpg_p720x720&_nc_cat=101&ccb=1-7&_nc_sid=127cfc&_nc_ohc=9QkSHhPb2mkQ7kNvgGN-rPE&_nc_ht=scontent-iad3-1.xx&edm=AKK4YLsEAAAA&oh=00_AYCvkE18ysuC5BPjq_1BV4cIScD-O4Z4bMbdOzUi472zrQ&oe=66E5696D","width":720}},"target":{"id":"1008907407697701","url":"https://www.facebook.com/photo.php?fbid=1008907407697701&set=a.208567717731678&type=3"},"type":"photo","url":"https://www.facebook.com/photo.php?fbid=1008907407697701&set=a.208567717731678&type=3"}]},"message":"Syksyn ekat futsalit. Hikisen hauskaa hommaa!","created_time":"2024-09-02T17:14:19+0000","id":"112275979305828_1008907434364365"},{"full_picture":"https://scontent-iad3-1.xx.fbcdn.net/v/t39.30808-6/457789810_18050100616855288_4915160408342386427_n.jpg?stp=dst-jpg_p720x720&_nc_cat=108&ccb=1-7&_nc_sid=127cfc&_nc_ohc=x-hCtCcYIrUQ7kNvgF2xl0C&_nc_ht=scontent-iad3-1.xx&edm=AKK4YLsEAAAA&oh=00_AYCFHfosXPjWawCp72GqcAYbo_oFX_kLy-rfrhHT901f0A&oe=66E55685","attachments":{"data":[{"description":"Ja näin pyörähti sunnuntaisäbäilytkin käyntiin🏑","media":{"image":{"height":900,"src":"https://scontent-iad3-1.xx.fbcdn.net/v/t39.30808-6/457789810_18050100616855288_4915160408342386427_n.jpg?stp=dst-jpg_p720x720&_nc_cat=108&ccb=1-7&_nc_sid=127cfc&_nc_ohc=x-hCtCcYIrUQ7kNvgF2xl0C&_nc_ht=scontent-iad3-1.xx&edm=AKK4YLsEAAAA&oh=00_AYCFHfosXPjWawCp72GqcAYbo_oFX_kLy-rfrhHT901f0A&oe=66E55685","width":720}},"target":{"id":"1008214794433629","url":"https://www.facebook.com/photo.php?fbid=1008214794433629&set=a.208567717731678&type=3"},"type":"photo","url":"https://www.facebook.com/photo.php?fbid=1008214794433629&set=a.208567717731678&type=3"}]},"message":"Ja näin pyörähti sunnuntaisäbäilytkin käyntiin🏑","created_time":"2024-09-01T15:50:11+0000","id":"112275979305828_1008214804433628"}]